{
  "timestamp": 1755607882620,
  "data": [
    {
      "ranking": 1,
      "symbol": "BTC",
      "price": 115309.9,
      "pricePct24h": 0.07,
      "long1h": 82150,
      "short1h": 42180,
      "long4h": 143550,
      "short4h": 882500,
      "long24h": 27260000,
      "short24h": 13220000
    },
    {
      "ranking": 2,
      "symbol": "ETH",
      "price": 4287.72,
      "pricePct24h": -0.98,
      "long1h": 920540,
      "short1h": 147480,
      "long4h": 1300000,
      "short4h": 11100000,
      "long24h": 73790000,
      "short24h": 41530000
    },
    {
      "ranking": 3,
      "symbol": "SOL",
      "price": 181.5,
      "pricePct24h": -0.36,
      "long1h": 31490,
      "short1h": 26620,
      "long4h": 47080,
      "short4h": 608820,
      "long24h": 10420000,
      "short24h": 3460000
    },
    {
      "ranking": 4,
      "symbol": "XRP",
      "price": 3.007,
      "pricePct24h": 0.87,
      "long1h": 10380,
      "short1h": 299.35,
      "long4h": 17630,
      "short4h": 108750,
      "long24h": 3990000,
      "short24h": 2410000
    },
    {
      "ranking": 5,
      "symbol": "DOGE",
      "price": 0.21926,
      "pricePct24h": -1.92,
      "long1h": 17480,
      "short1h": 5.09,
      "long4h": 34450,
      "short4h": 550690,
      "long24h": 10100000,
      "short24h": 1790000
    },
    {
      "ranking": 6,
      "symbol": "SUI",
      "price": 3.5875,
      "pricePct24h": 0.63,
      "long1h": 20280,
      "short1h": 256370,
      "long4h": 34010,
      "short4h": 412880,
      "long24h": 2210000,
      "short24h": 702410
    },
    {
      "ranking": 7,
      "symbol": "HYPE",
      "price": 43.677,
      "pricePct24h": 0.18,
      "long1h": 1090,
      "short1h": 6320,
      "long4h": 2320,
      "short4h": 29900,
      "long24h": 973440,
      "short24h": 112130
    },
    {
      "ranking": 8,
      "symbol": "ADA",
      "price": 0.9255,
      "pricePct24h": 1.79,
      "long1h": 124880,
      "short1h": 1960,
      "long4h": 212500,
      "short4h": 889340,
      "long24h": 2560000,
      "short24h": 2200000
    },
    {
      "ranking": 9,
      "symbol": "LINK",
      "price": 24.411,
      "pricePct24h": -3.09,
      "long1h": 45520,
      "short1h": 802.8,
      "long4h": 62100,
      "short4h": 246940,
      "long24h": 6360000,
      "short24h": 4170000
    },
    {
      "ranking": 10,
      "symbol": "BNB",
      "price": 844.01,
      "pricePct24h": 0.77,
      "long1h": 211.56,
      "short1h": 54390,
      "long4h": 220.02,
      "short4h": 104340,
      "long24h": 412380,
      "short24h": 514179.99999999994
    },
    {
      "ranking": 11,
      "symbol": "ENA",
      "price": 0.6587,
      "pricePct24h": -2.77,
      "long1h": 278.55,
      "short1h": 111.42,
      "long4h": 11100,
      "short4h": 23250,
      "long24h": 2670000,
      "short24h": 142650
    },
    {
      "ranking": 12,
      "symbol": "LTC",
      "price": 115.75,
      "pricePct24h": -1.19,
      "long1h": 619.93,
      "short1h": 580.5,
      "long4h": 2740,
      "short4h": 14610,
      "long24h": 898460,
      "short24h": 125060
    },
    {
      "ranking": 13,
      "symbol": "FARTCOIN",
      "price": 0.929,
      "pricePct24h": 1.05,
      "long1h": 7060,
      "short1h": 63740,
      "long4h": 22940,
      "short4h": 175810,
      "long24h": 1530000,
      "short24h": 469100
    },
    {
      "ranking": 14,
      "symbol": "AVAX",
      "price": 23.145,
      "pricePct24h": -3.24,
      "long1h": 4340,
      "short1h": 42370,
      "long4h": 7200,
      "short4h": 49010,
      "long24h": 1280000,
      "short24h": 190550
    },
    {
      "ranking": 15,
      "symbol": "UNI",
      "price": 10.418,
      "pricePct24h": -0.35,
      "long1h": 522.08,
      "short1h": 0,
      "long4h": 867.56,
      "short4h": 72730,
      "long24h": 784330,
      "short24h": 172590
    },
    {
      "ranking": 16,
      "symbol": "PEPE",
      "price": 0.000010709,
      "pricePct24h": -0.53,
      "long1h": 3730,
      "short1h": 0,
      "long4h": 3730,
      "short4h": 44700,
      "long24h": 1300000,
      "short24h": 77870
    },
    {
      "ranking": 17,
      "symbol": "TRX",
      "price": 0.35117,
      "pricePct24h": 0.91,
      "long1h": 1010,
      "short1h": 43910,
      "long4h": 1020,
      "short4h": 58930,
      "long24h": 202800,
      "short24h": 161940
    },
    {
      "ranking": 18,
      "symbol": "BCH",
      "price": 566.28,
      "pricePct24h": 0.45,
      "long1h": 5.67,
      "short1h": 33150,
      "long4h": 30.09,
      "short4h": 36840,
      "long24h": 245480,
      "short24h": 47490
    },
    {
      "ranking": 19,
      "symbol": "AAVE",
      "price": 285.37,
      "pricePct24h": -1.94,
      "long1h": 126.31,
      "short1h": 0,
      "long4h": 1610,
      "short4h": 16600,
      "long24h": 653310,
      "short24h": 81600
    },
    {
      "ranking": 20,
      "symbol": "DOT",
      "price": 3.859,
      "pricePct24h": -2.08,
      "long1h": 6640,
      "short1h": 0,
      "long4h": 6740,
      "short4h": 13400,
      "long24h": 393230,
      "short24h": 81270
    }
  ]
}