{
  "timestamp": 1754938845428,
  "data": [
    {
      "ranking": 1,
      "symbol": "BTC",
      "price": 119743,
      "pricePct24h": 1.03,
      "long1h": 6110000,
      "short1h": 256630,
      "long4h": 8560000,
      "short4h": 1610000,
      "long24h": 39720000,
      "short24h": 92880000
    },
    {
      "ranking": 2,
      "symbol": "ETH",
      "price": 4295.7,
      "pricePct24h": 1.45,
      "long1h": 5140000,
      "short1h": 1110000,
      "long4h": 11370000,
      "short4h": 13550000,
      "long24h": 66160000,
      "short24h": 74960000
    },
    {
      "ranking": 3,
      "symbol": "SOL",
      "price": 178.18,
      "pricePct24h": -2.46,
      "long1h": 1620000,
      "short1h": 4410,
      "long4h": 2720000,
      "short4h": 218990,
      "long24h": 13750000,
      "short24h": 3490000
    },
    {
      "ranking": 4,
      "symbol": "XRP",
      "price": 3.2039,
      "pricePct24h": -0.06,
      "long1h": 1770000,
      "short1h": 56540,
      "long4h": 3050000,
      "short4h": 392730,
      "long24h": 13840000,
      "short24h": 4310000
    },
    {
      "ranking": 5,
      "symbol": "DOGE",
      "price": 0.23102,
      "pricePct24h": -1.41,
      "long1h": 310540,
      "short1h": 17730,
      "long4h": 627380,
      "short4h": 457050,
      "long24h": 8670000,
      "short24h": 2410000
    },
    {
      "ranking": 6,
      "symbol": "SUI",
      "price": 3.7121,
      "pricePct24h": -4.33,
      "long1h": 806280,
      "short1h": 24540,
      "long4h": 1280000,
      "short4h": 49070,
      "long24h": 6310000,
      "short24h": 690110
    },
    {
      "ranking": 7,
      "symbol": "HYPE",
      "price": 43.975,
      "pricePct24h": -2.86,
      "long1h": 93640,
      "short1h": 694.42,
      "long4h": 140250,
      "short4h": 9770,
      "long24h": 480130,
      "short24h": 196150
    },
    {
      "ranking": 8,
      "symbol": "ENA",
      "price": 0.7994,
      "pricePct24h": 2.12,
      "long1h": 158320,
      "short1h": 11080,
      "long4h": 737770,
      "short4h": 261010,
      "long24h": 3710000,
      "short24h": 3070000
    },
    {
      "ranking": 9,
      "symbol": "ADA",
      "price": 0.7933,
      "pricePct24h": -1.7,
      "long1h": 299860,
      "short1h": 2660,
      "long4h": 396470,
      "short4h": 18030,
      "long24h": 3000000,
      "short24h": 528140
    },
    {
      "ranking": 10,
      "symbol": "LINK",
      "price": 21.599,
      "pricePct24h": -2.8,
      "long1h": 21350,
      "short1h": 0,
      "long4h": 54090,
      "short4h": 74690,
      "long24h": 1810000,
      "short24h": 907180
    },
    {
      "ranking": 11,
      "symbol": "BNB",
      "price": 810.44,
      "pricePct24h": 0.94,
      "long1h": 77960,
      "short1h": 1790,
      "long4h": 83180,
      "short4h": 33570,
      "long24h": 1110000,
      "short24h": 718090
    },
    {
      "ranking": 12,
      "symbol": "LTC",
      "price": 124.45,
      "pricePct24h": 0.45,
      "long1h": 70590,
      "short1h": 46580,
      "long4h": 123740,
      "short4h": 78650,
      "long24h": 1420000,
      "short24h": 1010000
    },
    {
      "ranking": 13,
      "symbol": "UNI",
      "price": 11.495,
      "pricePct24h": 4.66,
      "long1h": 14550,
      "short1h": 1610,
      "long4h": 315360,
      "short4h": 1740000,
      "long24h": 868240,
      "short24h": 1870000
    },
    {
      "ranking": 14,
      "symbol": "FARTCOIN",
      "price": 0.9849,
      "pricePct24h": -9.71,
      "long1h": 828600,
      "short1h": 14770,
      "long4h": 1010000,
      "short4h": 65230.00000000001,
      "long24h": 3790000,
      "short24h": 1200000
    },
    {
      "ranking": 15,
      "symbol": "AVAX",
      "price": 23.462,
      "pricePct24h": -2,
      "long1h": 97130,
      "short1h": 1100,
      "long4h": 207950,
      "short4h": 12990,
      "long24h": 1100000,
      "short24h": 513480
    },
    {
      "ranking": 16,
      "symbol": "BCH",
      "price": 590.36,
      "pricePct24h": 3.42,
      "long1h": 192.56,
      "short1h": 0,
      "long4h": 6420,
      "short4h": 48120,
      "long24h": 226330,
      "short24h": 864580
    },
    {
      "ranking": 17,
      "symbol": "PEPE",
      "price": 0.00001161,
      "pricePct24h": -4.01,
      "long1h": 92350,
      "short1h": 99.58,
      "long4h": 190100,
      "short4h": 172580,
      "long24h": 1660000,
      "short24h": 554270
    },
    {
      "ranking": 18,
      "symbol": "AAVE",
      "price": 299.08,
      "pricePct24h": -2.04,
      "long1h": 60900,
      "short1h": 1200,
      "long4h": 66660,
      "short4h": 97400,
      "long24h": 322740,
      "short24h": 460390
    },
    {
      "ranking": 19,
      "symbol": "TRX",
      "price": 0.34479,
      "pricePct24h": 1.71,
      "long1h": 1920,
      "short1h": 311.39,
      "long4h": 8770,
      "short4h": 18680,
      "long24h": 80740,
      "short24h": 81150
    },
    {
      "ranking": 20,
      "symbol": "1000PEPE",
      "price": 0.0116081,
      "pricePct24h": -4,
      "long1h": 112590,
      "short1h": 1880,
      "long4h": 241450,
      "short4h": 192060,
      "long24h": 5340000,
      "short24h": 1220000
    }
  ]
}