{
  "timestamp": 1754148414515,
  "data": [
    {
      "ranking": 1,
      "symbol": "BTC",
      "price": 113228.9,
      "pricePct24h": -1.34,
      "long1h": 2029999.9999999998,
      "short1h": 66480,
      "long4h": 3440000,
      "short4h": 146260,
      "long24h": 106580000,
      "short24h": 3580000
    },
    {
      "ranking": 2,
      "symbol": "ETH",
      "price": 3489.99,
      "pricePct24h": -2.73,
      "long1h": 3390000,
      "short1h": 144620,
      "long4h": 5410000,
      "short4h": 2100000,
      "long24h": 172230000,
      "short24h": 23760000
    },
    {
      "ranking": 3,
      "symbol": "SOL",
      "price": 163.59,
      "pricePct24h": -2.28,
      "long1h": 229780,
      "short1h": 27380,
      "long4h": 483730,
      "short4h": 256339.99999999997,
      "long24h": 25460000,
      "short24h": 4340000
    },
    {
      "ranking": 4,
      "symbol": "XRP",
      "price": 2.8885,
      "pricePct24h": -4.31,
      "long1h": 3830000,
      "short1h": 23400,
      "long4h": 4680000,
      "short4h": 184420,
      "long24h": 17470000,
      "short24h": 2540000
    },
    {
      "ranking": 5,
      "symbol": "DOGE",
      "price": 0.19742,
      "pricePct24h": -4.56,
      "long1h": 1290000,
      "short1h": 287480,
      "long4h": 1610000,
      "short4h": 346240,
      "long24h": 20240000,
      "short24h": 2430000
    },
    {
      "ranking": 6,
      "symbol": "SUI",
      "price": 3.4103,
      "pricePct24h": -2.52,
      "long1h": 321570,
      "short1h": 8600,
      "long4h": 371900,
      "short4h": 32700.000000000004,
      "long24h": 6370000,
      "short24h": 1010000
    },
    {
      "ranking": 7,
      "symbol": "HYPE",
      "price": 37.956,
      "pricePct24h": -2.6,
      "long1h": 13860,
      "short1h": 2510,
      "long4h": 30030,
      "short4h": 3320,
      "long24h": 2480000,
      "short24h": 69960
    },
    {
      "ranking": 8,
      "symbol": "BNB",
      "price": 751.04,
      "pricePct24h": -1.2,
      "long1h": 43270,
      "short1h": 14.97,
      "long4h": 46700,
      "short4h": 2200,
      "long24h": 2390000,
      "short24h": 296300
    },
    {
      "ranking": 9,
      "symbol": "ADA",
      "price": 0.7076,
      "pricePct24h": -2.68,
      "long1h": 126380,
      "short1h": 2140,
      "long4h": 206900,
      "short4h": 31830,
      "long24h": 3510000,
      "short24h": 212220
    },
    {
      "ranking": 10,
      "symbol": "ENA",
      "price": 0.5449,
      "pricePct24h": -8.31,
      "long1h": 1300000,
      "short1h": 44190,
      "long4h": 1380000,
      "short4h": 221080,
      "long24h": 5920000,
      "short24h": 1120000
    },
    {
      "ranking": 11,
      "symbol": "LTC",
      "price": 109.81,
      "pricePct24h": 4.26,
      "long1h": 8090,
      "short1h": 25030,
      "long4h": 8400,
      "short4h": 83210,
      "long24h": 1860000,
      "short24h": 296380
    },
    {
      "ranking": 12,
      "symbol": "LINK",
      "price": 15.96,
      "pricePct24h": -3.08,
      "long1h": 26630,
      "short1h": 268.02,
      "long4h": 38810,
      "short4h": 2640,
      "long24h": 2430000,
      "short24h": 30370
    },
    {
      "ranking": 13,
      "symbol": "FARTCOIN",
      "price": 0.9279,
      "pricePct24h": -8.21,
      "long1h": 149250,
      "short1h": 10910,
      "long4h": 220560,
      "short4h": 96420,
      "long24h": 5030000,
      "short24h": 588260
    },
    {
      "ranking": 14,
      "symbol": "AVAX",
      "price": 21.466,
      "pricePct24h": -2.43,
      "long1h": 32270.000000000004,
      "short1h": 0,
      "long4h": 33040,
      "short4h": 34350,
      "long24h": 2500000,
      "short24h": 81310
    },
    {
      "ranking": 15,
      "symbol": "UNI",
      "price": 9.042,
      "pricePct24h": 0.39,
      "long1h": 6810,
      "short1h": 4230,
      "long4h": 8710,
      "short4h": 11900,
      "long24h": 994520,
      "short24h": 49620
    },
    {
      "ranking": 16,
      "symbol": "PEPE",
      "price": 0.000010341,
      "pricePct24h": -1.84,
      "long1h": 38920,
      "short1h": 2650,
      "long4h": 51540,
      "short4h": 10960,
      "long24h": 1610000,
      "short24h": 410050
    },
    {
      "ranking": 17,
      "symbol": "AAVE",
      "price": 254.99,
      "pricePct24h": -0.68,
      "long1h": 1930,
      "short1h": 25.22,
      "long4h": 6160,
      "short4h": 25.22,
      "long24h": 1190000,
      "short24h": 25350
    },
    {
      "ranking": 18,
      "symbol": "TRX",
      "price": 0.32597,
      "pricePct24h": -0.2,
      "long1h": 667,
      "short1h": 51.1,
      "long4h": 800.26,
      "short4h": 129.89,
      "long24h": 558110,
      "short24h": 20640
    },
    {
      "ranking": 19,
      "symbol": "BCH",
      "price": 534.38,
      "pricePct24h": -2.7,
      "long1h": 3060,
      "short1h": 0,
      "long4h": 4910,
      "short4h": 82.86,
      "long24h": 2120000,
      "short24h": 13820
    },
    {
      "ranking": 20,
      "symbol": "1000PEPE",
      "price": 0.0103425,
      "pricePct24h": -1.85,
      "long1h": 84510,
      "short1h": 25260,
      "long4h": 172730,
      "short4h": 40600,
      "long24h": 2780000,
      "short24h": 410440
    }
  ]
}