{
  "timestamp": 1753588803181,
  "data": [
    {
      "ranking": 1,
      "symbol": "BTC",
      "price": 118162,
      "pricePct24h": 0.58,
      "long1h": 2600,
      "short1h": 1540,
      "long4h": 171600,
      "short4h": 1050000,
      "long24h": 763480,
      "short24h": 6750000
    },
    {
      "ranking": 2,
      "symbol": "ETH",
      "price": 3772.32,
      "pricePct24h": 0.84,
      "long1h": 362.59,
      "short1h": 51960,
      "long4h": 1590000,
      "short4h": 2980000,
      "long24h": 12250000,
      "short24h": 19350000
    },
    {
      "ranking": 3,
      "symbol": "SOL",
      "price": 187.13,
      "pricePct24h": 0.55,
      "long1h": 50010,
      "short1h": 90620,
      "long4h": 92800,
      "short4h": 357850,
      "long24h": 2840000,
      "short24h": 3680000
    },
    {
      "ranking": 4,
      "symbol": "XRP",
      "price": 3.1979,
      "pricePct24h": 1.7,
      "long1h": 35330,
      "short1h": 76.53,
      "long4h": 422340,
      "short4h": 120130,
      "long24h": 1900000,
      "short24h": 1880000
    },
    {
      "ranking": 5,
      "symbol": "DOGE",
      "price": 0.23913,
      "pricePct24h": 0.96,
      "long1h": 0,
      "short1h": 502.26,
      "long4h": 361360,
      "short4h": 240240,
      "long24h": 1780000,
      "short24h": 1610000
    },
    {
      "ranking": 6,
      "symbol": "SUI",
      "price": 4.2086,
      "pricePct24h": 5.61,
      "long1h": 19.21,
      "short1h": 103940,
      "long4h": 190130,
      "short4h": 183020,
      "long24h": 1480000,
      "short24h": 5140000
    },
    {
      "ranking": 7,
      "symbol": "HYPE",
      "price": 43.46,
      "pricePct24h": -1.78,
      "long1h": 0,
      "short1h": 744.69,
      "long4h": 57910,
      "short4h": 6390,
      "long24h": 144230,
      "short24h": 29280
    },
    {
      "ranking": 8,
      "symbol": "ADA",
      "price": 0.8286,
      "pricePct24h": 0.39,
      "long1h": 0,
      "short1h": 0,
      "long4h": 111980,
      "short4h": 81740,
      "long24h": 413370,
      "short24h": 249310
    },
    {
      "ranking": 9,
      "symbol": "ENA",
      "price": 0.613,
      "pricePct24h": 4.79,
      "long1h": 33250,
      "short1h": 11580,
      "long4h": 369850,
      "short4h": 630620,
      "long24h": 2270000,
      "short24h": 2650000
    },
    {
      "ranking": 10,
      "symbol": "BNB",
      "price": 794.78,
      "pricePct24h": 1.36,
      "long1h": 747.45,
      "short1h": 2260,
      "long4h": 787.31,
      "short4h": 391240,
      "long24h": 5720,
      "short24h": 974520
    },
    {
      "ranking": 11,
      "symbol": "LINK",
      "price": 18.687,
      "pricePct24h": 1.66,
      "long1h": 0,
      "short1h": 0,
      "long4h": 19130,
      "short4h": 18350,
      "long24h": 57960,
      "short24h": 56550
    },
    {
      "ranking": 12,
      "symbol": "FARTCOIN",
      "price": 1.3494,
      "pricePct24h": -1.03,
      "long1h": 650.05,
      "short1h": 9360,
      "long4h": 14360,
      "short4h": 34660,
      "long24h": 726780,
      "short24h": 216590
    },
    {
      "ranking": 13,
      "symbol": "LTC",
      "price": 114.56,
      "pricePct24h": 1.13,
      "long1h": 0,
      "short1h": 0,
      "long4h": 2490,
      "short4h": 6380,
      "long24h": 30280,
      "short24h": 92110
    },
    {
      "ranking": 14,
      "symbol": "PEPE",
      "price": 0.00001259,
      "pricePct24h": 0.06,
      "long1h": 0,
      "short1h": 303.89,
      "long4h": 0,
      "short4h": 15770,
      "long24h": 136820,
      "short24h": 85270
    },
    {
      "ranking": 15,
      "symbol": "AVAX",
      "price": 24.93,
      "pricePct24h": 3.53,
      "long1h": 0,
      "short1h": 1230,
      "long4h": 5220,
      "short4h": 1500,
      "long24h": 213860,
      "short24h": 330440
    },
    {
      "ranking": 16,
      "symbol": "UNI",
      "price": 10.581,
      "pricePct24h": 0.27,
      "long1h": 10.49,
      "short1h": 0,
      "long4h": 2980,
      "short4h": 23660,
      "long24h": 64480.00000000001,
      "short24h": 124420
    },
    {
      "ranking": 17,
      "symbol": "AAVE",
      "price": 295.9,
      "pricePct24h": -0.74,
      "long1h": 0,
      "short1h": 267.14,
      "long4h": 26.35,
      "short4h": 5590,
      "long24h": 102840,
      "short24h": 28940
    },
    {
      "ranking": 18,
      "symbol": "BCH",
      "price": 568.18,
      "pricePct24h": 2.37,
      "long1h": 0,
      "short1h": 0,
      "long4h": 15750,
      "short4h": 628420,
      "long24h": 29400,
      "short24h": 840290
    },
    {
      "ranking": 19,
      "symbol": "PENGU",
      "price": 0.04248,
      "pricePct24h": -0.71,
      "long1h": 22950,
      "short1h": 705.68,
      "long4h": 110870,
      "short4h": 406660,
      "long24h": 1030000,
      "short24h": 1720000
    },
    {
      "ranking": 20,
      "symbol": "1000PEPE",
      "price": 0.0125899,
      "pricePct24h": 0.05,
      "long1h": 0,
      "short1h": 4059.9999999999995,
      "long4h": 13120,
      "short4h": 39800,
      "long24h": 428500,
      "short24h": 485160
    }
  ]
}