{
  "timestamp": 1753822623763,
  "data": [
    {
      "ranking": 1,
      "symbol": "BTC",
      "price": 117288.2,
      "pricePct24h": -0.64,
      "long1h": 1800000,
      "short1h": 132350,
      "long4h": 1960000,
      "short4h": 916040,
      "long24h": 26250000,
      "short24h": 13010000
    },
    {
      "ranking": 2,
      "symbol": "ETH",
      "price": 3754.95,
      "pricePct24h": -0.89,
      "long1h": 3000000,
      "short1h": 595910,
      "long4h": 5040000,
      "short4h": 4019999.9999999995,
      "long24h": 64910000,
      "short24h": 29310000
    },
    {
      "ranking": 3,
      "symbol": "SOL",
      "price": 179.68,
      "pricePct24h": -2.64,
      "long1h": 357860,
      "short1h": 96970,
      "long4h": 543800,
      "short4h": 510920,
      "long24h": 15690000,
      "short24h": 2260000
    },
    {
      "ranking": 4,
      "symbol": "XRP",
      "price": 3.1062,
      "pricePct24h": -1.34,
      "long1h": 402500,
      "short1h": 74160,
      "long4h": 721240,
      "short4h": 435460,
      "long24h": 13350000,
      "short24h": 3230000
    },
    {
      "ranking": 5,
      "symbol": "DOGE",
      "price": 0.22071,
      "pricePct24h": -3.29,
      "long1h": 432900,
      "short1h": 59260,
      "long4h": 702640,
      "short4h": 302820,
      "long24h": 13280000,
      "short24h": 2560000
    },
    {
      "ranking": 6,
      "symbol": "SUI",
      "price": 3.7975,
      "pricePct24h": -3.75,
      "long1h": 285110,
      "short1h": 381.95,
      "long4h": 327710,
      "short4h": 134050,
      "long24h": 5870000,
      "short24h": 747100
    },
    {
      "ranking": 7,
      "symbol": "HYPE",
      "price": 43.26,
      "pricePct24h": -1.74,
      "long1h": 8740,
      "short1h": 831.28,
      "long4h": 9690,
      "short4h": 21600,
      "long24h": 658180,
      "short24h": 87350
    },
    {
      "ranking": 8,
      "symbol": "ADA",
      "price": 0.7727,
      "pricePct24h": -2.71,
      "long1h": 227320,
      "short1h": 325.24,
      "long4h": 251860,
      "short4h": 35820,
      "long24h": 4099999.9999999995,
      "short24h": 264090
    },
    {
      "ranking": 9,
      "symbol": "BNB",
      "price": 802.23,
      "pricePct24h": -2.85,
      "long1h": 43160,
      "short1h": 96.53,
      "long4h": 54860,
      "short4h": 87280,
      "long24h": 1990000,
      "short24h": 243640
    },
    {
      "ranking": 10,
      "symbol": "ENA",
      "price": 0.5643,
      "pricePct24h": -10.94,
      "long1h": 401360,
      "short1h": 3200,
      "long4h": 475110,
      "short4h": 61930,
      "long24h": 7750000,
      "short24h": 657100
    },
    {
      "ranking": 11,
      "symbol": "LINK",
      "price": 17.631,
      "pricePct24h": -2.97,
      "long1h": 68690,
      "short1h": 8150,
      "long4h": 107990,
      "short4h": 22910,
      "long24h": 1540000,
      "short24h": 240350
    },
    {
      "ranking": 12,
      "symbol": "LTC",
      "price": 107.91,
      "pricePct24h": -1.5,
      "long1h": 39730,
      "short1h": 130.03,
      "long4h": 42890,
      "short4h": 17310,
      "long24h": 1760000,
      "short24h": 87510
    },
    {
      "ranking": 13,
      "symbol": "FARTCOIN",
      "price": 1.0938,
      "pricePct24h": -6.73,
      "long1h": 139390,
      "short1h": 13870,
      "long4h": 219540,
      "short4h": 91250,
      "long24h": 2670000,
      "short24h": 561750
    },
    {
      "ranking": 14,
      "symbol": "AVAX",
      "price": 24.009,
      "pricePct24h": -5.41,
      "long1h": 161930,
      "short1h": 971.22,
      "long4h": 199610,
      "short4h": 98380,
      "long24h": 2330000,
      "short24h": 183270
    },
    {
      "ranking": 15,
      "symbol": "UNI",
      "price": 10.138,
      "pricePct24h": -3.02,
      "long1h": 8810,
      "short1h": 13040,
      "long4h": 12580,
      "short4h": 18310,
      "long24h": 923210,
      "short24h": 177240
    },
    {
      "ranking": 16,
      "symbol": "PEPE",
      "price": 0.000011309,
      "pricePct24h": -5.74,
      "long1h": 215970,
      "short1h": 824.9,
      "long4h": 281910,
      "short4h": 25910,
      "long24h": 2450000,
      "short24h": 161380
    },
    {
      "ranking": 17,
      "symbol": "AAVE",
      "price": 280.07,
      "pricePct24h": -3.23,
      "long1h": 19350,
      "short1h": 0,
      "long4h": 43250,
      "short4h": 8300,
      "long24h": 1030000,
      "short24h": 83430
    },
    {
      "ranking": 18,
      "symbol": "TRX",
      "price": 0.33462,
      "pricePct24h": 4.13,
      "long1h": 95780,
      "short1h": 1750,
      "long4h": 97860,
      "short4h": 1790,
      "long24h": 799290,
      "short24h": 2550000
    },
    {
      "ranking": 19,
      "symbol": "BCH",
      "price": 561.92,
      "pricePct24h": -2.58,
      "long1h": 52130,
      "short1h": 501.24,
      "long4h": 52780,
      "short4h": 1030,
      "long24h": 1570000,
      "short24h": 101730
    },
    {
      "ranking": 20,
      "symbol": "1000PEPE",
      "price": 0.0113085,
      "pricePct24h": -5.74,
      "long1h": 230300,
      "short1h": 4530,
      "long4h": 415250,
      "short4h": 51310,
      "long24h": 4970000,
      "short24h": 280420
    }
  ]
}