{
  "timestamp": 1755165308257,
  "data": [
    {
      "ranking": 1,
      "symbol": "BTC",
      "price": 121661.9,
      "pricePct24h": 1.32,
      "long1h": 89180,
      "short1h": 218050,
      "long4h": 9400000,
      "short4h": 645870,
      "long24h": 26120000,
      "short24h": 112580000
    },
    {
      "ranking": 2,
      "symbol": "ETH",
      "price": 4756.83,
      "pricePct24h": 1.2,
      "long1h": 446650,
      "short1h": 690500,
      "long4h": 3790000,
      "short4h": 3770000,
      "long24h": 54830000,
      "short24h": 72350000
    },
    {
      "ranking": 3,
      "symbol": "SOL",
      "price": 205.12,
      "pricePct24h": 1.74,
      "long1h": 50080,
      "short1h": 167820,
      "long4h": 4510000,
      "short4h": 548740,
      "long24h": 15620000,
      "short24h": 17560000
    },
    {
      "ranking": 4,
      "symbol": "XRP",
      "price": 3.2418,
      "pricePct24h": -1.28,
      "long1h": 132360,
      "short1h": 4019.9999999999995,
      "long4h": 4090000,
      "short4h": 29800,
      "long24h": 11900000,
      "short24h": 3740000
    },
    {
      "ranking": 5,
      "symbol": "DOGE",
      "price": 0.2423,
      "pricePct24h": -2.86,
      "long1h": 1660000,
      "short1h": 2009.9999999999998,
      "long4h": 4530000,
      "short4h": 397410,
      "long24h": 9560000,
      "short24h": 4300000
    },
    {
      "ranking": 6,
      "symbol": "SUI",
      "price": 3.9824,
      "pricePct24h": -0.19,
      "long1h": 20920,
      "short1h": 1720,
      "long4h": 1060000,
      "short4h": 16620,
      "long24h": 3640000,
      "short24h": 2130000
    },
    {
      "ranking": 7,
      "symbol": "HYPE",
      "price": 47.097,
      "pricePct24h": 4.13,
      "long1h": 8270,
      "short1h": 2340,
      "long4h": 95980,
      "short4h": 6780,
      "long24h": 282210,
      "short24h": 960230
    },
    {
      "ranking": 8,
      "symbol": "ADA",
      "price": 0.9946,
      "pricePct24h": 13.51,
      "long1h": 92840,
      "short1h": 72730,
      "long4h": 1530000,
      "short4h": 1050000,
      "long24h": 3520000,
      "short24h": 8070000
    },
    {
      "ranking": 9,
      "symbol": "ENA",
      "price": 0.7303,
      "pricePct24h": -9.12,
      "long1h": 56560,
      "short1h": 50290,
      "long4h": 3110000,
      "short4h": 93120,
      "long24h": 5520000,
      "short24h": 525410
    },
    {
      "ranking": 10,
      "symbol": "LINK",
      "price": 23.782,
      "pricePct24h": 0.11,
      "long1h": 2440,
      "short1h": 77290,
      "long4h": 929000,
      "short4h": 126750,
      "long24h": 2170000,
      "short24h": 793620
    },
    {
      "ranking": 11,
      "symbol": "BNB",
      "price": 867.42,
      "pricePct24h": 1.44,
      "long1h": 933.73,
      "short1h": 78120,
      "long4h": 122090,
      "short4h": 508030,
      "long24h": 468350,
      "short24h": 1950000
    },
    {
      "ranking": 12,
      "symbol": "LTC",
      "price": 128.77,
      "pricePct24h": -2.48,
      "long1h": 16190.000000000002,
      "short1h": 0,
      "long4h": 716340,
      "short4h": 73170,
      "long24h": 1110000,
      "short24h": 668070
    },
    {
      "ranking": 13,
      "symbol": "FARTCOIN",
      "price": 1.1261,
      "pricePct24h": 1.29,
      "long1h": 13940,
      "short1h": 27930,
      "long4h": 311570,
      "short4h": 265150,
      "long24h": 2680000,
      "short24h": 2720000
    },
    {
      "ranking": 14,
      "symbol": "AVAX",
      "price": 25.281,
      "pricePct24h": -0.04,
      "long1h": 3210,
      "short1h": 427.23,
      "long4h": 417580,
      "short4h": 1050,
      "long24h": 743190,
      "short24h": 265530
    },
    {
      "ranking": 15,
      "symbol": "UNI",
      "price": 11.568,
      "pricePct24h": -4.54,
      "long1h": 48850,
      "short1h": 0,
      "long4h": 270280,
      "short4h": 3040,
      "long24h": 745730,
      "short24h": 1460000
    },
    {
      "ranking": 16,
      "symbol": "AAVE",
      "price": 327.3,
      "pricePct24h": 0.66,
      "long1h": 27230,
      "short1h": 588.01,
      "long4h": 104050,
      "short4h": 1060,
      "long24h": 215260,
      "short24h": 697860
    },
    {
      "ranking": 17,
      "symbol": "TRX",
      "price": 0.36895,
      "pricePct24h": 2.94,
      "long1h": 0,
      "short1h": 55310,
      "long4h": 31390,
      "short4h": 85890,
      "long24h": 219300,
      "short24h": 626470
    },
    {
      "ranking": 18,
      "symbol": "PEPE",
      "price": 0.000011968,
      "pricePct24h": -3.93,
      "long1h": 21910,
      "short1h": 478.04,
      "long4h": 1160000,
      "short4h": 15110,
      "long24h": 2820000,
      "short24h": 1100000
    },
    {
      "ranking": 19,
      "symbol": "BCH",
      "price": 609.33,
      "pricePct24h": -0.04,
      "long1h": 6000,
      "short1h": 2550,
      "long4h": 322010,
      "short4h": 2780,
      "long24h": 567990,
      "short24h": 575820
    },
    {
      "ranking": 20,
      "symbol": "1000PEPE",
      "price": 0.0119666,
      "pricePct24h": -3.95,
      "long1h": 105900,
      "short1h": 25380,
      "long4h": 899480,
      "short4h": 32009.999999999996,
      "long24h": 2120000,
      "short24h": 791310
    }
  ]
}