{
  "timestamp": 1755455804789,
  "data": [
    {
      "ranking": 1,
      "symbol": "BTC",
      "price": 117798.7,
      "pricePct24h": 0.12,
      "long1h": 3490,
      "short1h": 981.7,
      "long4h": 2160000,
      "short4h": 309050,
      "long24h": 2830000,
      "short24h": 7470000
    },
    {
      "ranking": 2,
      "symbol": "ETH",
      "price": 4515.22,
      "pricePct24h": 2.31,
      "long1h": 410060,
      "short1h": 83380,
      "long4h": 4660000,
      "short4h": 2100000,
      "long24h": 13920000,
      "short24h": 50870000
    },
    {
      "ranking": 3,
      "symbol": "SOL",
      "price": 193.07,
      "pricePct24h": 2.83,
      "long1h": 96630,
      "short1h": 3210,
      "long4h": 541860,
      "short4h": 2069999.9999999998,
      "long24h": 1300000,
      "short24h": 6100000
    },
    {
      "ranking": 4,
      "symbol": "XRP",
      "price": 3.1044,
      "pricePct24h": 0.13,
      "long1h": 530890,
      "short1h": 538.72,
      "long4h": 771000,
      "short4h": 169650,
      "long24h": 1200000,
      "short24h": 955750
    },
    {
      "ranking": 5,
      "symbol": "DOGE",
      "price": 0.23534,
      "pricePct24h": 2.66,
      "long1h": 350480,
      "short1h": 0,
      "long4h": 1470000,
      "short4h": 2480000,
      "long24h": 1940000,
      "short24h": 4970000
    },
    {
      "ranking": 6,
      "symbol": "SUI",
      "price": 3.8333,
      "pricePct24h": 2.32,
      "long1h": 4630,
      "short1h": 231.33,
      "long4h": 127390,
      "short4h": 141770,
      "long24h": 207870,
      "short24h": 799970
    },
    {
      "ranking": 7,
      "symbol": "ADA",
      "price": 0.9592,
      "pricePct24h": 4.97,
      "long1h": 189190,
      "short1h": 0,
      "long4h": 262200,
      "short4h": 178470,
      "long24h": 1150000,
      "short24h": 2720000
    },
    {
      "ranking": 8,
      "symbol": "HYPE",
      "price": 46.683,
      "pricePct24h": 0.09,
      "long1h": 5080,
      "short1h": 0,
      "long4h": 137230,
      "short4h": 2090,
      "long24h": 224690,
      "short24h": 151960
    },
    {
      "ranking": 9,
      "symbol": "LINK",
      "price": 25.807,
      "pricePct24h": 15.86,
      "long1h": 23120,
      "short1h": 15170,
      "long4h": 367260,
      "short4h": 2490000,
      "long24h": 678710,
      "short24h": 6180000
    },
    {
      "ranking": 10,
      "symbol": "BNB",
      "price": 856.28,
      "pricePct24h": 2.54,
      "long1h": 1460,
      "short1h": 0,
      "long4h": 31510,
      "short4h": 77100,
      "long24h": 39430,
      "short24h": 1040000
    },
    {
      "ranking": 11,
      "symbol": "ENA",
      "price": 0.712,
      "pricePct24h": -0.66,
      "long1h": 8160,
      "short1h": 0,
      "long4h": 160180,
      "short4h": 12820,
      "long24h": 1020000,
      "short24h": 597980
    },
    {
      "ranking": 12,
      "symbol": "LTC",
      "price": 121.69,
      "pricePct24h": 1.56,
      "long1h": 3310,
      "short1h": 1350,
      "long4h": 43370,
      "short4h": 22920,
      "long24h": 201700,
      "short24h": 349280
    },
    {
      "ranking": 13,
      "symbol": "AVAX",
      "price": 25.391,
      "pricePct24h": 5.89,
      "long1h": 15840,
      "short1h": 49790,
      "long4h": 23140,
      "short4h": 391130,
      "long24h": 85390,
      "short24h": 800380
    },
    {
      "ranking": 14,
      "symbol": "FARTCOIN",
      "price": 0.9664,
      "pricePct24h": 3.34,
      "long1h": 39220,
      "short1h": 123.06,
      "long4h": 163250,
      "short4h": 506090,
      "long24h": 477020,
      "short24h": 903770
    },
    {
      "ranking": 15,
      "symbol": "UNI",
      "price": 11.133,
      "pricePct24h": 1.73,
      "long1h": 3570,
      "short1h": 0,
      "long4h": 48920,
      "short4h": 31810,
      "long24h": 81610,
      "short24h": 149810
    },
    {
      "ranking": 16,
      "symbol": "PEPE",
      "price": 0.00001125,
      "pricePct24h": 2.28,
      "long1h": 20040,
      "short1h": 972.35,
      "long4h": 402920,
      "short4h": 705470,
      "long24h": 407430,
      "short24h": 1090000
    },
    {
      "ranking": 17,
      "symbol": "TRX",
      "price": 0.35315,
      "pricePct24h": 1.61,
      "long1h": 844.43,
      "short1h": 568.61,
      "long4h": 968.92,
      "short4h": 1820,
      "long24h": 4790,
      "short24h": 211480
    },
    {
      "ranking": 18,
      "symbol": "AAVE",
      "price": 304.34,
      "pricePct24h": 3.47,
      "long1h": 26380,
      "short1h": 0,
      "long4h": 71570,
      "short4h": 33210,
      "long24h": 86650,
      "short24h": 166020
    },
    {
      "ranking": 19,
      "symbol": "BCH",
      "price": 584.02,
      "pricePct24h": 0.65,
      "long1h": 1150,
      "short1h": 0,
      "long4h": 158300,
      "short4h": 3920,
      "long24h": 159590,
      "short24h": 126460
    },
    {
      "ranking": 20,
      "symbol": "1000PEPE",
      "price": 0.0112499,
      "pricePct24h": 2.28,
      "long1h": 100960,
      "short1h": 0,
      "long4h": 181160,
      "short4h": 388630,
      "long24h": 243640,
      "short24h": 652960
    }
  ]
}