{
  "timestamp": 1754664743582,
  "data": [
    {
      "ranking": 1,
      "symbol": "BTC",
      "price": 116532.5,
      "pricePct24h": 0.18,
      "long1h": 973790,
      "short1h": 2380000,
      "long4h": 1080000,
      "short4h": 4450000,
      "long24h": 8780000,
      "short24h": 23620000
    },
    {
      "ranking": 2,
      "symbol": "ETH",
      "price": 3970.54,
      "pricePct24h": 4.16,
      "long1h": 4440000,
      "short1h": 7640000,
      "long4h": 5160000,
      "short4h": 27420000,
      "long24h": 25980000,
      "short24h": 92730000
    },
    {
      "ranking": 3,
      "symbol": "SOL",
      "price": 176.21,
      "pricePct24h": 3.52,
      "long1h": 508170,
      "short1h": 1250000,
      "long4h": 796830,
      "short4h": 3100000,
      "long24h": 7140000,
      "short24h": 10470000
    },
    {
      "ranking": 4,
      "symbol": "XRP",
      "price": 3.2806,
      "pricePct24h": 7.76,
      "long1h": 2430000,
      "short1h": 435220,
      "long4h": 2570000,
      "short4h": 911350,
      "long24h": 9640000,
      "short24h": 20750000
    },
    {
      "ranking": 5,
      "symbol": "DOGE",
      "price": 0.22356,
      "pricePct24h": 5.03,
      "long1h": 721980,
      "short1h": 943910,
      "long4h": 784160,
      "short4h": 1290000,
      "long24h": 2290000,
      "short24h": 7960000
    },
    {
      "ranking": 6,
      "symbol": "SUI",
      "price": 3.79,
      "pricePct24h": 1.89,
      "long1h": 286600,
      "short1h": 113810,
      "long4h": 331410,
      "short4h": 239100,
      "long24h": 880200,
      "short24h": 2930000
    },
    {
      "ranking": 7,
      "symbol": "HYPE",
      "price": 40.99,
      "pricePct24h": 3.95,
      "long1h": 12410,
      "short1h": 2550,
      "long4h": 14390,
      "short4h": 51260,
      "long24h": 48760,
      "short24h": 352980
    },
    {
      "ranking": 8,
      "symbol": "ADA",
      "price": 0.7899,
      "pricePct24h": 4.06,
      "long1h": 216600,
      "short1h": 44510,
      "long4h": 277360,
      "short4h": 173260,
      "long24h": 872800,
      "short24h": 1310000
    },
    {
      "ranking": 9,
      "symbol": "BNB",
      "price": 790.09,
      "pricePct24h": 2.35,
      "long1h": 9890,
      "short1h": 74130,
      "long4h": 11640,
      "short4h": 131520,
      "long24h": 195320,
      "short24h": 2580000
    },
    {
      "ranking": 10,
      "symbol": "ENA",
      "price": 0.6286,
      "pricePct24h": 1.5,
      "long1h": 56400,
      "short1h": 230910,
      "long4h": 65140,
      "short4h": 324140,
      "long24h": 1240000,
      "short24h": 1400000
    },
    {
      "ranking": 11,
      "symbol": "LINK",
      "price": 19.462,
      "pricePct24h": 10.5,
      "long1h": 47890,
      "short1h": 148120,
      "long4h": 60970,
      "short4h": 390260,
      "long24h": 380570,
      "short24h": 1920000
    },
    {
      "ranking": 12,
      "symbol": "LTC",
      "price": 122.13,
      "pricePct24h": 1.45,
      "long1h": 121140,
      "short1h": 135870,
      "long4h": 122310,
      "short4h": 172690,
      "long24h": 600960,
      "short24h": 1300000
    },
    {
      "ranking": 13,
      "symbol": "FARTCOIN",
      "price": 1.022,
      "pricePct24h": 3.92,
      "long1h": 68500,
      "short1h": 137870,
      "long4h": 154180,
      "short4h": 157080,
      "long24h": 1590000,
      "short24h": 1030000
    },
    {
      "ranking": 14,
      "symbol": "AVAX",
      "price": 23.376,
      "pricePct24h": 3.5,
      "long1h": 30350,
      "short1h": 56490,
      "long4h": 31310,
      "short4h": 77530,
      "long24h": 328040,
      "short24h": 503330
    },
    {
      "ranking": 15,
      "symbol": "UNI",
      "price": 10.646,
      "pricePct24h": 5.99,
      "long1h": 48400,
      "short1h": 6630,
      "long4h": 50590,
      "short4h": 87340,
      "long24h": 166630,
      "short24h": 962100
    },
    {
      "ranking": 16,
      "symbol": "PEPE",
      "price": 0.000011268,
      "pricePct24h": 4.3,
      "long1h": 29190,
      "short1h": 81840,
      "long4h": 49780,
      "short4h": 101730,
      "long24h": 693700,
      "short24h": 873210
    },
    {
      "ranking": 17,
      "symbol": "AAVE",
      "price": 285.46,
      "pricePct24h": 4.95,
      "long1h": 18460,
      "short1h": 52390,
      "long4h": 44640,
      "short4h": 60020,
      "long24h": 191300,
      "short24h": 676630
    },
    {
      "ranking": 18,
      "symbol": "BCH",
      "price": 580.96,
      "pricePct24h": 0.88,
      "long1h": 98.31,
      "short1h": 114220,
      "long4h": 1650,
      "short4h": 141520,
      "long24h": 53610,
      "short24h": 575620
    },
    {
      "ranking": 19,
      "symbol": "TRX",
      "price": 0.33859,
      "pricePct24h": -0.41,
      "long1h": 498.02,
      "short1h": 1500,
      "long4h": 917.59,
      "short4h": 1660,
      "long24h": 214200,
      "short24h": 41990
    },
    {
      "ranking": 20,
      "symbol": "1000PEPE",
      "price": 0.0112677,
      "pricePct24h": 4.27,
      "long1h": 54730,
      "short1h": 130340,
      "long4h": 98930,
      "short4h": 354940,
      "long24h": 508900,
      "short24h": 1840000
    }
  ]
}